divide_seq.py
divide_seq-5.22.dist-info/LICENSE
divide_seq-5.22.dist-info/METADATA
divide_seq-5.22.dist-info/WHEEL
divide_seq-5.22.dist-info/top_level.txt
divide_seq-5.22.dist-info/RECORD
