Metadata-Version: 2.1
Name: divide-seq
Version: 5.22
Summary: Divide amplicon sequences
Home-page: https://github.com/wpwupingwp/divide
Author: Ping Wu
Author-email: wpwupingwp@outlook.com
License: GNU AGPL v3
Platform: UNKNOWN
Classifier: Development Status :: 4 - Beta
Classifier: Intended Audience :: Developers
Classifier: Intended Audience :: Science/Research
Classifier: License :: OSI Approved :: GNU Affero General Public License v3
Classifier: Operating System :: OS Independent
Classifier: Programming Language :: Python :: 3.5
Classifier: Programming Language :: Python :: 3.6
Classifier: Programming Language :: Python :: 3.7
Classifier: Topic :: Scientific/Engineering :: Bio-Informatics
Requires-Dist: biopython (>=1.72)
Requires-Dist: pip (>=18.0)
Requires-Dist: regex (>=2019.08.19)
Requires-Dist: wheel (>=0.32.3)
